SST/__init__.py
SST/input.txt
SST/licence.txt
sst_v_2-0.2.dist-info/METADATA
sst_v_2-0.2.dist-info/WHEEL
sst_v_2-0.2.dist-info/top_level.txt
sst_v_2-0.2.dist-info/RECORD
